txdps/__init__.py
txdps/enums.py
txdps/txdps.py
txdps-0.0.1.dist-info/LICENSE
txdps-0.0.1.dist-info/METADATA
txdps-0.0.1.dist-info/WHEEL
txdps-0.0.1.dist-info/top_level.txt
txdps-0.0.1.dist-info/RECORD
