Metadata-Version: 2.1
Name: txdps
Version: 0.0.1
Summary: Python package to deal with Texas DPS Appointments
Author-email: Han-Hsuan Lin <hhl@utexas.edu>
Project-URL: Homepage, https://github.com/jercymat/txdps.py
Project-URL: Bug Tracker, https://github.com/jercymat/txdps.py/issues
Classifier: Programming Language :: Python :: 3
Classifier: License :: OSI Approved :: GNU General Public License v3 (GPLv3)
Classifier: Operating System :: OS Independent
Requires-Python: >=3.7
License-File: LICENSE
